{
    "fold_results": [
        {
            "fold": 0,
            "num_train_samples": 74,
            "num_test_samples": 13,
            "best_metrics": {
                "val_cindex": 0.8572072072072071,
                "val_loss": 0.10834591264526049
            }
        },
        {
            "fold": 1,
            "num_train_samples": 69,
            "num_test_samples": 18,
            "best_metrics": {
                "val_cindex": 0.8185446009389671,
                "val_loss": 0.10805756573875745
            }
        },
        {
            "fold": 2,
            "num_train_samples": 63,
            "num_test_samples": 24,
            "best_metrics": {
                "val_cindex": 0.7725333333333333,
                "val_loss": 0.3680255388220151
            }
        },
        {
            "fold": 3,
            "num_train_samples": 66,
            "num_test_samples": 21,
            "best_metrics": {
                "val_cindex": 0.6921367521367522,
                "val_loss": 0.043321916336814564
            }
        },
        {
            "fold": 4,
            "num_train_samples": 76,
            "num_test_samples": 11,
            "best_metrics": {
                "val_cindex": 0.7565217391304346,
                "val_loss": 0.0
            }
        }
    ],
    "mean_metrics": {
        "val_cindex": 0.7793887265493389,
        "val_loss": 0.12555018670856952
    },
    "std_metrics": {
        "val_cindex": 0.056163513066353705,
        "val_loss": 0.12800047894274885
    }
}