{
    "fold_results": [
        {
            "fold": 0,
            "num_train_samples": 74,
            "num_test_samples": 13,
            "best_metrics": {
                "val_cindex": 0.5881164749463399,
                "val_loss": 0.12211470926801364
            }
        },
        {
            "fold": 1,
            "num_train_samples": 69,
            "num_test_samples": 18,
            "best_metrics": {
                "val_cindex": 0.747763588031133,
                "val_loss": 0.17981976916392645
            }
        },
        {
            "fold": 2,
            "num_train_samples": 63,
            "num_test_samples": 24,
            "best_metrics": {
                "val_cindex": 0.6241547644138337,
                "val_loss": 0.35067706753810246
            }
        },
        {
            "fold": 3,
            "num_train_samples": 66,
            "num_test_samples": 21,
            "best_metrics": {
                "val_cindex": 0.6508396128813426,
                "val_loss": 0.04332260973751545
            }
        },
        {
            "fold": 4,
            "num_train_samples": 76,
            "num_test_samples": 11,
            "best_metrics": {
                "val_cindex": 0.6024242301781972,
                "val_loss": 0.0
            }
        }
    ],
    "mean_metrics": {
        "val_cindex": 0.6426597340901694,
        "val_loss": 0.1391868311415116
    },
    "std_metrics": {
        "val_cindex": 0.05665691012768885,
        "val_loss": 0.12266502027659958
    }
}
